uk_tides_mcp/__init__.py
uk_tides_mcp/stations.json
uk_tides_mcp/tides.py
uk_tides_mcp-1.0.0.dist-info/WHEEL
uk_tides_mcp-1.0.0.dist-info/entry_points.txt
uk_tides_mcp-1.0.0.dist-info/METADATA
uk_tides_mcp-1.0.0.dist-info/RECORD
