Metadata-Version: 2.4
Name: uk-tides-mcp
Version: 1.0.0
Summary: Model Context Protocol (MCP) server for UK low & high beach tides
Author: Kai Hendry
Author-email: Kai Hendry <hendry@iki.fi>
License-Expression: MIT
Requires-Dist: httpx>=0.28.1
Requires-Dist: mcp[cli]>=1.12.4
Requires-Python: >=3.11
Project-URL: Repository, https://github.com/kaihendry/uk-tides-mcp
